setup.py
CydraTwistedGit.egg-info/PKG-INFO
CydraTwistedGit.egg-info/SOURCES.txt
CydraTwistedGit.egg-info/dependency_links.txt
CydraTwistedGit.egg-info/entry_points.txt
CydraTwistedGit.egg-info/namespace_packages.txt
CydraTwistedGit.egg-info/requires.txt
CydraTwistedGit.egg-info/top_level.txt
cydraplugins/__init__.py
cydraplugins/twistedgit/__init__.py