Metadata-Version: 1.0
Name: CydraTwistedGit
Version: 0.1
Summary: Cydra plugin for ssh-based repository serving
Home-page: http://www.cydra.org
Author: Manuel Stocker
Author-email: mensi@vis.ethz.ch
License: GPL
Keywords: cydra ssh
Platform: UNKNOWN
